pic2square2icon/README.MD
pic2square2icon/__init__.py
pic2square2icon/requirements.txt
pic2square2icon/thirdparty.json
pic2square2icon-0.11.dist-info/LICENSE.rst
pic2square2icon-0.11.dist-info/METADATA
pic2square2icon-0.11.dist-info/WHEEL
pic2square2icon-0.11.dist-info/top_level.txt
pic2square2icon-0.11.dist-info/RECORD
