Metadata-Version: 2.1
Name: pic2square2icon
Version: 0.11
Summary: 2 functions that provide convenient and efficient ways to resize images to a square with custom backgrounds and convert images to the ICO format
Home-page: https://github.com/hansalemaos/pic2square2icon
Author: Johannes Fischer
Author-email: aulasparticularesdealemaosp@gmail.com
License: MIT
Keywords: ico,convert,posts
Classifier: Development Status :: 4 - Beta
Classifier: Programming Language :: Python :: 3 :: Only
Classifier: Programming Language :: Python :: 3.10
Classifier: Topic :: Software Development :: Libraries :: Python Modules
Classifier: Topic :: Utilities
License-File: LICENSE.rst
Requires-Dist: Pillow
Requires-Dist: fabisschomagut
Requires-Dist: ignoreexceptions
Requires-Dist: touchtouch
